docstringtest/__init__.py
docstringtest-0.1.0.data/scripts/docstringtest
docstringtest-0.1.0.dist-info/DESCRIPTION.rst
docstringtest-0.1.0.dist-info/METADATA
docstringtest-0.1.0.dist-info/RECORD
docstringtest-0.1.0.dist-info/WHEEL
docstringtest-0.1.0.dist-info/metadata.json
docstringtest-0.1.0.dist-info/top_level.txt
