Metadata-Version: 2.0
Name: docstringtest
Version: 0.1.0
Summary: Procedure to check for valid Sphinx ReST docstrings
Home-page: https://github.com/jakelever/docstringtest
Author: Jake Lever
Author-email: jake.lever@gmail.com
License: MIT
Keywords: docstring testing
Platform: UNKNOWN
Classifier: Development Status :: 4 - Beta
Classifier: Intended Audience :: Developers
Classifier: Topic :: Software Development :: Documentation
Classifier: Topic :: Software Development :: Testing
Classifier: License :: OSI Approved :: MIT License
Classifier: Programming Language :: Python :: 2.7
Classifier: Programming Language :: Python :: 3.4
Classifier: Programming Language :: Python :: 3.5
Classifier: Programming Language :: Python :: 3.6
